pshook/__init__.py
pshook/wrapper.py
pshook-0.0.8.dist-info/LICENSE
pshook-0.0.8.dist-info/METADATA
pshook-0.0.8.dist-info/WHEEL
pshook-0.0.8.dist-info/top_level.txt
pshook-0.0.8.dist-info/RECORD
