Metadata-Version: 2.1
Name: pshook
Version: 0.0.8
Summary: A small tool that enables monitoring of executable files
Home-page: https://bitbucket.org/jakobsg/ladon
Author: Jakob Simon-Gaarde
Author-email: jakobsg@simon-gaarde.dk
License: UNKNOWN
Platform: UNKNOWN
Classifier: Programming Language :: Python :: 2
Classifier: Programming Language :: Python :: 3
Classifier: License :: OSI Approved :: MIT License
Classifier: Operating System :: OS Independent
Requires-Python: >=2.6
Requires-Dist: psutil (==5.6.3)
